soferai/__init__.py
soferai/client.py
soferai/environment.py
soferai/py.typed
soferai/version.py
soferai/balance/__init__.py
soferai/balance/client.py
soferai/balance/errors/__init__.py
soferai/balance/errors/user_not_found.py
soferai/balance/types/__init__.py
soferai/balance/types/balance.py
soferai/categories/__init__.py
soferai/categories/client.py
soferai/categories/errors/__init__.py
soferai/categories/errors/category_already_exists.py
soferai/categories/errors/category_not_found.py
soferai/categories/types/__init__.py
soferai/categories/types/add_transcription_to_category_request.py
soferai/categories/types/add_transcription_to_category_response.py
soferai/categories/types/category.py
soferai/categories/types/category_transcription.py
soferai/categories/types/create_category_request.py
soferai/categories/types/delete_category_response.py
soferai/categories/types/remove_transcription_from_category_response.py
soferai/categories/types/update_category_request.py
soferai/core/__init__.py
soferai/core/api_error.py
soferai/core/client_wrapper.py
soferai/core/datetime_utils.py
soferai/core/file.py
soferai/core/http_client.py
soferai/core/jsonable_encoder.py
soferai/core/pydantic_utilities.py
soferai/core/query_encoder.py
soferai/core/remove_none_from_dict.py
soferai/core/request_options.py
soferai/core/serialization.py
soferai/health/__init__.py
soferai/health/client.py
soferai/health/types/__init__.py
soferai/health/types/health_response.py
soferai/link/__init__.py
soferai/link/client.py
soferai/link/errors/__init__.py
soferai/link/errors/link_error.py
soferai/link/errors/link_not_found.py
soferai/link/errors/link_not_supported.py
soferai/link/types/__init__.py
soferai/link/types/link_request.py
soferai/link/types/link_response.py
soferai/link/types/site.py
soferai/live_transcription_ws/__init__.py
soferai/live_transcription_ws/types/__init__.py
soferai/live_transcription_ws/types/audio_chunk.py
soferai/live_transcription_ws/types/transcript_chunk.py
soferai-0.13.0.dist-info/METADATA
soferai-0.13.0.dist-info/WHEEL
soferai-0.13.0.dist-info/RECORD
