Metadata-Version: 2.4
Name: soferai
Version: 0.13.0
Summary: Soferai Python Client
Project-URL: Repository, https://github.com/soferai/soferai-py
Author-email: Matanya Loewenthal <matanya@sofer.ai>, Zach Fish <zach@sofer.ai>
Classifier: Intended Audience :: Developers
Classifier: Operating System :: MacOS
Classifier: Operating System :: Microsoft :: Windows
Classifier: Operating System :: OS Independent
Classifier: Operating System :: POSIX
Classifier: Operating System :: POSIX :: Linux
Classifier: Programming Language :: Python
Classifier: Programming Language :: Python :: 3
Classifier: Programming Language :: Python :: 3.8
Classifier: Programming Language :: Python :: 3.9
Classifier: Programming Language :: Python :: 3.10
Classifier: Programming Language :: Python :: 3.11
Classifier: Programming Language :: Python :: 3.12
Classifier: Topic :: Software Development :: Libraries :: Python Modules
Classifier: Typing :: Typed
Requires-Python: >=3.9
Requires-Dist: httpx>=0.27.2
Requires-Dist: pydantic-core>=2.27.2
Requires-Dist: pydantic>=2.10.4
Requires-Dist: typing-extensions>=4.12.2
